promptolution/exemplar_selectors/__init__.py
promptolution/exemplar_selectors/base_exemplar_selector.py
promptolution/exemplar_selectors/random_search_selector.py
promptolution/exemplar_selectors/random_selector.py
promptolution/helpers.py
promptolution/llms/__init__.py
promptolution/llms/api_llm.py
promptolution/llms/base_llm.py
promptolution/llms/local_llm.py
promptolution/llms/vllm.py
promptolution/optimizers/__init__.py
promptolution/optimizers/base_optimizer.py
promptolution/optimizers/capo.py
promptolution/optimizers/evoprompt_de.py
promptolution/optimizers/evoprompt_ga.py
promptolution/optimizers/opro.py
promptolution/optimizers/templates.py
promptolution/predictors/__init__.py
promptolution/predictors/base_predictor.py
promptolution/predictors/classifier.py
promptolution/tasks/__init__.py
promptolution/tasks/base_task.py
promptolution/tasks/classification_tasks.py
promptolution/tasks/judge_tasks.py
promptolution/tasks/reward_tasks.py
promptolution/utils/__init__.py
promptolution/utils/callbacks.py
promptolution/utils/config.py
promptolution/utils/formatting.py
promptolution/utils/logging.py
promptolution/utils/prompt_creation.py
promptolution/utils/test_statistics.py
promptolution/utils/token_counter.py
promptolution-2.1.0.dist-info/LICENSE
promptolution-2.1.0.dist-info/METADATA
promptolution-2.1.0.dist-info/WHEEL
promptolution-2.1.0.dist-info/RECORD
