Metadata-Version: 2.3
Name: promptolution
Version: 2.1.0
Summary: A framework for prompt optimization and a zoo of prompt optimization algorithms.
Author: Tom Zehle, Moritz Schlager, Timo Heiß
Requires-Python: >=3.10,<3.13
Classifier: Programming Language :: Python :: 3
Classifier: Programming Language :: Python :: 3.10
Classifier: Programming Language :: Python :: 3.11
Classifier: Programming Language :: Python :: 3.12
Provides-Extra: api
Provides-Extra: transformers
Provides-Extra: vllm
Requires-Dist: fastparquet (>=2024.11.0,<2025.0.0)
Requires-Dist: numpy (>=1.26.0,<3.0.0)
Requires-Dist: openai (>=1.0.0,<2.0.0) ; extra == "api"
Requires-Dist: pandas (>=2.2.2,<3.0.0)
Requires-Dist: requests (>=2.31.0,<3.0.0) ; extra == "api"
Requires-Dist: scikit-learn (>=1.5.2,<2.0.0)
Requires-Dist: tqdm (>=4.66.5,<5.0.0)
Requires-Dist: transformers (>=4.48.0,<5.0.0) ; extra == "transformers"
Requires-Dist: vllm (>=0.10.1.1,<0.11.0.0) ; extra == "vllm"
